simplesim/__init__.py
simplesim/base.py
simplesim/simulation.py
simplesim-1.0.0.dist-info/LICENSE
simplesim-1.0.0.dist-info/METADATA
simplesim-1.0.0.dist-info/WHEEL
simplesim-1.0.0.dist-info/top_level.txt
simplesim-1.0.0.dist-info/RECORD
