Metadata-Version: 2.1
Name: simplesim
Version: 1.0.0
Summary: A simple and generic framework for quickly and easily creating a simulation environment
Home-page: https://github.com/MeelonUsk/simplesim
Author: Adam Morrissett
Author-email: me@adamlm.com
License: UNKNOWN
Keywords: simple generic simulation environment framework
Platform: UNKNOWN
Classifier: Programming Language :: Python :: 3
Classifier: License :: OSI Approved :: MIT License
Classifier: Operating System :: OS Independent
Requires-Python: >=3.5
